mrnet4gmns/__init__.py
mrnet4gmns/settings.py
mrnet4gmns/io/__init__.py
mrnet4gmns/io/load_from_csv.py
mrnet4gmns/io/output_mrnet.py
mrnet4gmns/io/util_io.py
mrnet4gmns/io/writefile.py
mrnet4gmns/movement/__init__.py
mrnet4gmns/movement/autoconintd.py
mrnet4gmns/movement/autoconm.py
mrnet4gmns/movement/generate_movements.py
mrnet4gmns/movement/util_mvmt.py
mrnet4gmns/multiresolution/__init__.py
mrnet4gmns/multiresolution/build_mrnet.py
mrnet4gmns/multiresolution/netgen.py
mrnet4gmns/networkclass/__init__.py
mrnet4gmns/networkclass/basenet.py
mrnet4gmns/networkclass/macronet.py
mrnet4gmns/networkclass/mesonet.py
mrnet4gmns/networkclass/micronet.py
mrnet4gmns/osmnet/__init__.py
mrnet4gmns/osmnet/build_net.py
mrnet4gmns/osmnet/check_args.py
mrnet4gmns/osmnet/combine_links.py
mrnet4gmns/osmnet/complex_intersection.py
mrnet4gmns/osmnet/enrich_net_info.py
mrnet4gmns/osmnet/osmclasses.py
mrnet4gmns/osmnet/pois.py
mrnet4gmns/osmnet/read_from_osm.py
mrnet4gmns/osmnet/wayfilters.py
mrnet4gmns/utils/__init__.py
mrnet4gmns/utils/util.py
mrnet4gmns/utils/util_coord.py
mrnet4gmns/utils/util_geo.py
mrnet4gmns-0.1.1.dist-info/licenses/LICENSE
mrnet4gmns-0.1.1.dist-info/METADATA
mrnet4gmns-0.1.1.dist-info/WHEEL
mrnet4gmns-0.1.1.dist-info/top_level.txt
mrnet4gmns-0.1.1.dist-info/RECORD
