Metadata-Version: 2.4
Name: mrnet4gmns
Version: 0.1.1
Summary: A multi-resolution network builder for GMNS networks
Author: Yajun Liu
Author-email: Yajun Liu <yajunliu@asu.edu>
License: MIT
Keywords: multi-resolution,network,GMNS,transportation,GIS,OSM,meso,micro
Classifier: Development Status :: 3 - Alpha
Classifier: Intended Audience :: Science/Research
Classifier: Intended Audience :: Developers
Classifier: License :: OSI Approved :: MIT License
Classifier: Programming Language :: Python :: 3
Classifier: Programming Language :: Python :: 3.8
Classifier: Programming Language :: Python :: 3.9
Classifier: Programming Language :: Python :: 3.10
Classifier: Programming Language :: Python :: 3.11
Classifier: Programming Language :: Python :: 3.12
Classifier: Topic :: Scientific/Engineering :: GIS
Requires-Python: >=3.8
License-File: LICENSE
Requires-Dist: numpy>=1.20.0
Requires-Dist: pandas>=1.3.0
Requires-Dist: shapely>=2.0.0
Requires-Dist: geopandas>=0.10.0
Requires-Dist: networkx>=2.6.0
Requires-Dist: osmium>=3.5.0
Provides-Extra: dev
Requires-Dist: pytest>=7.0.0; extra == "dev"
Requires-Dist: pytest-cov>=3.0.0; extra == "dev"
Requires-Dist: black>=22.0.0; extra == "dev"
Requires-Dist: flake8>=4.0.0; extra == "dev"
Dynamic: author
Dynamic: license-file
Dynamic: requires-python
